blobz/__init__.py
blobz/bin/imgpkg
blobz-0.0.10.dist-info/LICENSE
blobz-0.0.10.dist-info/METADATA
blobz-0.0.10.dist-info/WHEEL
blobz-0.0.10.dist-info/top_level.txt
blobz-0.0.10.dist-info/RECORD
