Metadata-Version: 2.1
Name: blobz
Version: 0.0.10
Summary: Artifact storage using OCI registries
Home-page: https://github.com/aunum/blobz
Maintainer: Patrick Barker
Project-URL: Documentation, https://github.com/aunum/blobz
Project-URL: Code, https://github.com/aunum/blobz
Project-URL: Issue tracker, https://github.com/aunum/blobz
Requires-Python: >=3.6
License-File: LICENSE
Requires-Dist: jsonpickle
